{"2Federalincometaxwithheld": 29853.34, "6Medicaretaxwithheld": 1967.6065, "3Socialsecuritywages": 135697.0, "aEmployeessocialsecuritynumber": "102-67-1962", "4Socialsecuritytaxwithheld": 8413.214, "5Medicarewagesandtips": 135697.0, "1Wagestipsothercompensation": 135697.0, "EmployersstateIDnumber": "09-87654321", "Thirdpartysickpay": "NOT_SELECTED", "bEmployeridentificationnumberEIN": "09-87654321", "17Stateincometax": 8589.6201, "Retirementplan": "NOT_SELECTED", "Statutoryemployee": "NOT_SELECTED", "State": "NY", "Lastname": "Leith-Harvey", "cEmployersnameaddressandZIPcode": "Example Authority of New York, 456 Example St, New York, New York 10001", "16Statewagestipsetc": 135697.0, "Employeesfirstnameandinitial": "Annemarie", "fEmployeesaddressandZIPcode": "6 Kinsman Terrace, New York City, NY, 10009"}