{"1Wagestipsothercompensation": 259133.0, "6Medicaretaxwithheld": 3757.4285, "2Federalincometaxwithheld": 82922.56, "aEmployeessocialsecuritynumber": "416-09-0627", "4Socialsecuritytaxwithheld": 16066.246, "5Medicarewagesandtips": 259133.0, "3Socialsecuritywages": 259133.0, "cEmployersnameaddressandZIPcode": "AnyCompany Gas Networks, 123 Main St, New York, New York 10001", "Lastname": "Bredbury", "16Statewagestipsetc": 259133.0, "EmployersstateIDnumber": "12-34567890", "Thirdpartysickpay": "NOT_SELECTED", "Retirementplan": "NOT_SELECTED", "17Stateincometax": 17750.6105, "Statutoryemployee": "NOT_SELECTED", "bEmployeridentificationnumberEIN": "12-34567890", "State": "NY", "Employeesfirstnameandinitial": "Cassandre", "fEmployeesaddressandZIPcode": "8 Susan Parkway, Albany, NY, 10023"}