{"6Medicaretaxwithheld": 2809.027, "3Socialsecuritywages": 193726.0, "aEmployeessocialsecuritynumber": "464-34-7218", "1Wagestipsothercompensation": 193726.0, "2Federalincometaxwithheld": 46494.24, "4Socialsecuritytaxwithheld": 12011.012, "5Medicarewagesandtips": 193726.0, "cEmployersnameaddressandZIPcode": "AnyCompany Gas Networks, 123 Main St, New York, New York 10001", "EmployersstateIDnumber": "12-34567890", "Thirdpartysickpay": "NOT_SELECTED", "Statutoryemployee": "NOT_SELECTED", "Retirementplan": "NOT_SELECTED", "Lastname": "lacovacci", "17Stateincometax": 12262.8558, "State": "NY", "bEmployeridentificationnumberEIN": "12-34567890", "Employeesfirstnameandinitial": "Lawton", "16Statewagestipsetc": 193726.0, "fEmployeesaddressandZIPcode": "0 Vidon Circle, New York City, NY, 10018"}