{"2Federalincometaxwithheld": 10519.52, "3Socialsecuritywages": 47816.0, "6Medicaretaxwithheld": 693.332, "5Medicarewagesandtips": 47816.0, "1Wagestipsothercompensation": 47816.0, "4Socialsecuritytaxwithheld": 2964.592, "17Stateincometax": 2854.6152, "bEmployeridentificationnumberEIN": "09-87654321", "aEmployeessocialsecuritynumber": "899-26-3096", "Retirementplan": "NOT_SELECTED", "cEmployersnameaddressandZIPcode": "Example Authority of New York, 456 Example St, New York, New York 10001", "Statutoryemployee": "NOT_SELECTED", "Thirdpartysickpay": "NOT_SELECTED", "Lastname": "Geertz", "EmployersstateIDnumber": "09-87654321", "State": "NY", "Employeesfirstnameandinitial": "Nettie", "16Statewagestipsetc": 47816.0, "fEmployeesaddressandZIPcode": "69 Canary Drive, Buffalo, NY, 10006"}