{"6Medicaretaxwithheld": 885.9645, "aEmployeessocialsecuritynumber": "250-57-7220", "2Federalincometaxwithheld": 13442.22, "4Socialsecuritytaxwithheld": 3788.262, "3Socialsecuritywages": 61101.0, "5Medicarewagesandtips": 61101.0, "1Wagestipsothercompensation": 61101.0, "Lastname": "Fairlamb", "cEmployersnameaddressandZIPcode": "Example Authority of New York, 456 Example St, New York, New York 10001", "EmployersstateIDnumber": "09-87654321", "Statutoryemployee": "NOT_SELECTED", "Thirdpartysickpay": "NOT_SELECTED", "16Statewagestipsetc": 61101.0, "Retirementplan": "NOT_SELECTED", "17Stateincometax": 3647.7297, "Employeesfirstnameandinitial": "Onida", "bEmployeridentificationnumberEIN": "09-87654321", "State": "NY", "fEmployeesaddressandZIPcode": "8 Ridgeway Trail, Albany, NY, 10011"}