{"5Medicarewagesandtips": 281185.0, "6Medicaretaxwithheld": 4077.1825, "3Socialsecuritywages": 281185.0, "2Federalincometaxwithheld": 89979.2, "4Socialsecuritytaxwithheld": 17433.47, "1Wagestipsothercompensation": 281185.0, "aEmployeessocialsecuritynumber": "563-12-3400", "17Stateincometax": 19261.1725, "bEmployeridentificationnumberEIN": "09-87654321", "cEmployersnameaddressandZIPcode": "Example Authority of New York, 456 Example St, New York, New York 10001", "Thirdpartysickpay": "NOT_SELECTED", "Retirementplan": "NOT_SELECTED", "Statutoryemployee": "NOT_SELECTED", "State": "NY", "Lastname": "Axworthy", "16Statewagestipsetc": 281185.0, "EmployersstateIDnumber": "09-87654321", "Employeesfirstnameandinitial": "Stephanus", "fEmployeesaddressandZIPcode": "2762 Merrick Crossing, New York City, NY, 10016"}