{"2Federalincometaxwithheld": 28147.24, "6Medicaretaxwithheld": 1855.159, "5Medicarewagesandtips": 127942.0, "1Wagestipsothercompensation": 127942.0, "3Socialsecuritywages": 127942.0, "17Stateincometax": 8098.7286, "4Socialsecuritytaxwithheld": 7932.404, "aEmployeessocialsecuritynumber": "575-38-3527", "bEmployeridentificationnumberEIN": "09-87654321", "cEmployersnameaddressandZIPcode": "Example Authority of New York, 456 Example St, New York, New York 10001", "EmployersstateIDnumber": "09-87654321", "Retirementplan": "NOT_SELECTED", "Statutoryemployee": "NOT_SELECTED", "Thirdpartysickpay": "NOT_SELECTED", "Lastname": "Andres", "State": "NY", "Employeesfirstnameandinitial": "Tyrus", "16Statewagestipsetc": 127942.0, "fEmployeesaddressandZIPcode": "30356 Bunker Hill Way, Buffalo, NY, 10012"}